njinja/__init__.py
njinja-0.3.dist-info/METADATA
njinja-0.3.dist-info/WHEEL
njinja-0.3.dist-info/top_level.txt
njinja-0.3.dist-info/RECORD
