Metadata-Version: 2.4
Name: njinja
Version: 0.3
Summary: General-purpose lightweight meta-build system for Ninja
Author-email: Ximin Luo <infinity0@pwned.gg>
Project-URL: Homepage, https://github.com/infinity0/njinja
Project-URL: Bug Tracker, https://github.com/infinity0/njinja/issues
Classifier: Programming Language :: Python :: 3
Classifier: License :: OSI Approved :: MIT License
Classifier: Operating System :: OS Independent
Requires-Python: >=3.9
Requires-Dist: jinja2
